LICENSE
README.md
setup.py
PyFilesDownloader/__init__.py
PyFilesDownloader.egg-info/PKG-INFO
PyFilesDownloader.egg-info/SOURCES.txt
PyFilesDownloader.egg-info/dependency_links.txt
PyFilesDownloader.egg-info/requires.txt
PyFilesDownloader.egg-info/top_level.txt
PyFilesDownloader/Qt/__init__.py
PyFilesDownloader/Qt/m3u8_thread.py
PyFilesDownloader/Qt/qt.py
PyFilesDownloader/Qt/stream_thread.py
PyFilesDownloader/aio/__init__.py
PyFilesDownloader/aio/m3u8.py
PyFilesDownloader/aio/stream.py
PyFilesDownloader/loader/__init__.py
PyFilesDownloader/loader/base.py
PyFilesDownloader/loader/stream.py
PyFilesDownloader/loader/m3u8/__init__.py
PyFilesDownloader/loader/m3u8/cryptoModel.py
PyFilesDownloader/loader/m3u8/loader.py
PyFilesDownloader/loader/m3u8/method.py
tests/test_async_n3u8.py
tests/test_m3u8.py
tests/test_stream.py
tests/test_thread.py