Metadata-Version: 2.1
Name: PyFilesDownloader
Version: 1.0.9
Summary: 一个下载文件的Python库
Home-page: https://gitee.com/chiyaun/PyFilesDownloader
Author: 赤鸢仙人
Author-email: 2640610281@qq.com
Project-URL: Project Homepage, https://gitee.com/chiyaun/PyFilesDownloader
Project-URL: Documentation, https://gitee.com/chiyaun/PyFilesDownloader/blob/master/README.md
Project-URL: Source Code, https://gitee.com/chiyaun/PyFilesDownloader
Project-URL: Bug Tracker, https://gitee.com/chiyaun/PyFilesDownloader/issues
Keywords: 一个下载文件的Python库
Platform: all
Classifier: Intended Audience :: Developers
Classifier: Operating System :: OS Independent
Classifier: Natural Language :: Chinese (Simplified)
Classifier: Programming Language :: Python
Classifier: Programming Language :: Python :: 3.8
Requires-Python: >=3.7
License-File: LICENSE
Requires-Dist: requests
Requires-Dist: pycryptodome
Requires-Dist: m3u8
